{
    "metric": "roc_auc",
    "eval_score": 0.9363158820546958,
    "n_trial": 74,
    "dataset": "train_0356_delta_elevators",
    "model": {
        "normalize_proj_diff": "max-detached",
        "detached_vec_norm": true,
        "detached_pivots": false,
        "use_svm_score": true,
        "train_gamma": false,
        "use_kernel_weight": true,
        "train_std": false,
        "reg_type": "lin",
        "combine_type": "embd",
        "n_vectors": 672,
        "n_kernel": 215,
        "kernel_std": 0.3250557380331315,
        "use_kernel": "lin",
        "use_score": "rbf",
        "reg_wt": 0.0011408943645057215
    },
    "training": {
        "batch_size": 64,
        "eval_batch_size": 64,
        "weight_decay": 0.0,
        "optimizer": "adamw",
        "lr": 2.59273701379186e-05
    }
}